{
    "customers": [
        {
            "demand": 16,
            "index": 20,
            "x": 39,
            "y": 4
        },
        {
            "demand": 20,
            "index": 21,
            "x": 50,
            "y": 22
        },
        {
            "demand": 17,
            "index": 22,
            "x": 44,
            "y": 7
        },
        {
            "demand": 13,
            "index": 23,
            "x": 42,
            "y": 6
        },
        {
            "demand": 12,
            "index": 24,
            "x": 43,
            "y": 24
        },
        {
            "demand": 15,
            "index": 25,
            "x": 44,
            "y": 25
        },
        {
            "demand": 15,
            "index": 26,
            "x": 15,
            "y": 1
        },
        {
            "demand": 18,
            "index": 27,
            "x": 41,
            "y": 26
        },
        {
            "demand": 16,
            "index": 28,
            "x": 38,
            "y": 7
        },
        {
            "demand": 17,
            "index": 29,
            "x": 23,
            "y": 29
        },
        {
            "demand": 17,
            "index": 30,
            "x": 41,
            "y": 33
        },
        {
            "demand": 18,
            "index": 31,
            "x": 37,
            "y": 23
        },
        {
            "demand": 14,
            "index": 32,
            "x": 48,
            "y": 3
        },
        {
            "demand": 16,
            "index": 33,
            "x": 2,
            "y": 35
        },
        {
            "demand": 17,
            "index": 34,
            "x": 46,
            "y": 2
        },
        {
            "demand": 18,
            "index": 35,
            "x": 7,
            "y": 1
        },
        {
            "demand": 12,
            "index": 36,
            "x": 9,
            "y": 20
        },
        {
            "demand": 15,
            "index": 37,
            "x": 25,
            "y": 6
        },
        {
            "demand": 12,
            "index": 38,
            "x": 9,
            "y": 8
        },
        {
            "demand": 11,
            "index": 39,
            "x": 49,
            "y": 11
        },
        {
            "demand": 20,
            "index": 40,
            "x": 12,
            "y": 31
        },
        {
            "demand": 13,
            "index": 41,
            "x": 3,
            "y": 12
        },
        {
            "demand": 18,
            "index": 42,
            "x": 37,
            "y": 21
        },
        {
            "demand": 20,
            "index": 43,
            "x": 50,
            "y": 34
        },
        {
            "demand": 11,
            "index": 44,
            "x": 12,
            "y": 25
        },
        {
            "demand": 13,
            "index": 45,
            "x": 13,
            "y": 24
        },
        {
            "demand": 20,
            "index": 46,
            "x": 32,
            "y": 32
        },
        {
            "demand": 20,
            "index": 47,
            "x": 29,
            "y": 34
        },
        {
            "demand": 19,
            "index": 48,
            "x": 2,
            "y": 17
        },
        {
            "demand": 16,
            "index": 49,
            "x": 16,
            "y": 2
        },
        {
            "demand": 15,
            "index": 50,
            "x": 39,
            "y": 16
        },
        {
            "demand": 19,
            "index": 51,
            "x": 41,
            "y": 32
        },
        {
            "demand": 16,
            "index": 52,
            "x": 25,
            "y": 18
        },
        {
            "demand": 15,
            "index": 53,
            "x": 31,
            "y": 36
        },
        {
            "demand": 12,
            "index": 54,
            "x": 47,
            "y": 6
        },
        {
            "demand": 11,
            "index": 55,
            "x": 17,
            "y": 14
        },
        {
            "demand": 16,
            "index": 56,
            "x": 2,
            "y": 20
        },
        {
            "demand": 14,
            "index": 57,
            "x": 40,
            "y": 26
        },
        {
            "demand": 14,
            "index": 58,
            "x": 29,
            "y": 27
        },
        {
            "demand": 18,
            "index": 59,
            "x": 27,
            "y": 23
        },
        {
            "demand": 13,
            "index": 60,
            "x": 35,
            "y": 36
        },
        {
            "demand": 19,
            "index": 61,
            "x": 6,
            "y": 30
        },
        {
            "demand": 15,
            "index": 62,
            "x": 41,
            "y": 7
        },
        {
            "demand": 17,
            "index": 63,
            "x": 22,
            "y": 23
        },
        {
            "demand": 14,
            "index": 64,
            "x": 43,
            "y": 10
        },
        {
            "demand": 13,
            "index": 65,
            "x": 43,
            "y": 35
        },
        {
            "demand": 15,
            "index": 66,
            "x": 32,
            "y": 14
        },
        {
            "demand": 12,
            "index": 67,
            "x": 4,
            "y": 32
        },
        {
            "demand": 11,
            "index": 68,
            "x": 6,
            "y": 8
        },
        {
            "demand": 14,
            "index": 69,
            "x": 20,
            "y": 19
        },
        {
            "demand": 16,
            "index": 70,
            "x": 18,
            "y": 11
        },
        {
            "demand": 19,
            "index": 71,
            "x": 43,
            "y": 27
        },
        {
            "demand": 16,
            "index": 72,
            "x": 14,
            "y": 28
        },
        {
            "demand": 15,
            "index": 73,
            "x": 29,
            "y": 23
        },
        {
            "demand": 15,
            "index": 74,
            "x": 43,
            "y": 25
        },
        {
            "demand": 15,
            "index": 75,
            "x": 17,
            "y": 35
        },
        {
            "demand": 18,
            "index": 76,
            "x": 49,
            "y": 19
        },
        {
            "demand": 20,
            "index": 77,
            "x": 19,
            "y": 26
        },
        {
            "demand": 14,
            "index": 78,
            "x": 24,
            "y": 33
        },
        {
            "demand": 17,
            "index": 79,
            "x": 15,
            "y": 32
        },
        {
            "demand": 20,
            "index": 80,
            "x": 2,
            "y": 36
        },
        {
            "demand": 12,
            "index": 81,
            "x": 9,
            "y": 22
        },
        {
            "demand": 16,
            "index": 82,
            "x": 45,
            "y": 33
        },
        {
            "demand": 15,
            "index": 83,
            "x": 11,
            "y": 30
        },
        {
            "demand": 18,
            "index": 84,
            "x": 49,
            "y": 21
        },
        {
            "demand": 20,
            "index": 85,
            "x": 34,
            "y": 3
        },
        {
            "demand": 15,
            "index": 86,
            "x": 21,
            "y": 19
        },
        {
            "demand": 15,
            "index": 87,
            "x": 29,
            "y": 11
        },
        {
            "demand": 18,
            "index": 88,
            "x": 21,
            "y": 35
        },
        {
            "demand": 13,
            "index": 89,
            "x": 35,
            "y": 16
        },
        {
            "demand": 12,
            "index": 90,
            "x": 35,
            "y": 32
        },
        {
            "demand": 14,
            "index": 91,
            "x": 21,
            "y": 9
        },
        {
            "demand": 19,
            "index": 92,
            "x": 45,
            "y": 26
        },
        {
            "demand": 11,
            "index": 93,
            "x": 32,
            "y": 36
        },
        {
            "demand": 15,
            "index": 94,
            "x": 39,
            "y": 2
        },
        {
            "demand": 11,
            "index": 95,
            "x": 37,
            "y": 5
        },
        {
            "demand": 12,
            "index": 96,
            "x": 50,
            "y": 32
        },
        {
            "demand": 20,
            "index": 97,
            "x": 21,
            "y": 6
        },
        {
            "demand": 18,
            "index": 98,
            "x": 41,
            "y": 35
        },
        {
            "demand": 16,
            "index": 99,
            "x": 45,
            "y": 28
        },
        {
            "demand": 18,
            "index": 100,
            "x": 40,
            "y": 24
        },
        {
            "demand": 15,
            "index": 101,
            "x": 33,
            "y": 18
        },
        {
            "demand": 14,
            "index": 102,
            "x": 14,
            "y": 24
        },
        {
            "demand": 15,
            "index": 103,
            "x": 32,
            "y": 17
        },
        {
            "demand": 15,
            "index": 104,
            "x": 11,
            "y": 14
        },
        {
            "demand": 15,
            "index": 105,
            "x": 25,
            "y": 13
        },
        {
            "demand": 13,
            "index": 106,
            "x": 12,
            "y": 33
        },
        {
            "demand": 11,
            "index": 107,
            "x": 38,
            "y": 5
        },
        {
            "demand": 17,
            "index": 108,
            "x": 3,
            "y": 17
        },
        {
            "demand": 15,
            "index": 109,
            "x": 15,
            "y": 9
        },
        {
            "demand": 18,
            "index": 110,
            "x": 47,
            "y": 8
        },
        {
            "demand": 13,
            "index": 111,
            "x": 24,
            "y": 10
        },
        {
            "demand": 16,
            "index": 112,
            "x": 44,
            "y": 26
        },
        {
            "demand": 18,
            "index": 113,
            "x": 23,
            "y": 13
        },
        {
            "demand": 14,
            "index": 114,
            "x": 14,
            "y": 7
        },
        {
            "demand": 12,
            "index": 115,
            "x": 4,
            "y": 17
        },
        {
            "demand": 18,
            "index": 116,
            "x": 14,
            "y": 25
        },
        {
            "demand": 15,
            "index": 117,
            "x": 13,
            "y": 2
        },
        {
            "demand": 18,
            "index": 118,
            "x": 2,
            "y": 11
        },
        {
            "demand": 19,
            "index": 119,
            "x": 27,
            "y": 20
        },
        {
            "demand": 17,
            "index": 120,
            "x": 47,
            "y": 4
        },
        {
            "demand": 17,
            "index": 121,
            "x": 44,
            "y": 1
        },
        {
            "demand": 18,
            "index": 122,
            "x": 22,
            "y": 22
        },
        {
            "demand": 19,
            "index": 123,
            "x": 51,
            "y": 5
        },
        {
            "demand": 15,
            "index": 124,
            "x": 41,
            "y": 18
        },
        {
            "demand": 17,
            "index": 125,
            "x": 10,
            "y": 8
        },
        {
            "demand": 11,
            "index": 126,
            "x": 2,
            "y": 9
        },
        {
            "demand": 12,
            "index": 127,
            "x": 8,
            "y": 26
        },
        {
            "demand": 11,
            "index": 128,
            "x": 12,
            "y": 20
        },
        {
            "demand": 16,
            "index": 129,
            "x": 21,
            "y": 36
        },
        {
            "demand": 19,
            "index": 130,
            "x": 30,
            "y": 33
        },
        {
            "demand": 12,
            "index": 131,
            "x": 41,
            "y": 24
        },
        {
            "demand": 20,
            "index": 132,
            "x": 20,
            "y": 32
        },
        {
            "demand": 15,
            "index": 133,
            "x": 37,
            "y": 3
        },
        {
            "demand": 20,
            "index": 134,
            "x": 31,
            "y": 21
        },
        {
            "demand": 19,
            "index": 135,
            "x": 34,
            "y": 13
        },
        {
            "demand": 20,
            "index": 136,
            "x": 14,
            "y": 35
        },
        {
            "demand": 11,
            "index": 137,
            "x": 43,
            "y": 7
        },
        {
            "demand": 12,
            "index": 138,
            "x": 5,
            "y": 11
        },
        {
            "demand": 18,
            "index": 139,
            "x": 23,
            "y": 33
        },
        {
            "demand": 16,
            "index": 140,
            "x": 42,
            "y": 13
        },
        {
            "demand": 16,
            "index": 141,
            "x": 48,
            "y": 12
        },
        {
            "demand": 14,
            "index": 142,
            "x": 11,
            "y": 7
        },
        {
            "demand": 18,
            "index": 143,
            "x": 1,
            "y": 29
        },
        {
            "demand": 20,
            "index": 144,
            "x": 3,
            "y": 16
        },
        {
            "demand": 15,
            "index": 145,
            "x": 6,
            "y": 24
        },
        {
            "demand": 17,
            "index": 146,
            "x": 27,
            "y": 34
        },
        {
            "demand": 20,
            "index": 147,
            "x": 41,
            "y": 25
        },
        {
            "demand": 13,
            "index": 148,
            "x": 34,
            "y": 35
        },
        {
            "demand": 20,
            "index": 149,
            "x": 5,
            "y": 7
        },
        {
            "demand": 19,
            "index": 150,
            "x": 46,
            "y": 1
        },
        {
            "demand": 15,
            "index": 151,
            "x": 25,
            "y": 10
        },
        {
            "demand": 12,
            "index": 152,
            "x": 36,
            "y": 2
        },
        {
            "demand": 18,
            "index": 153,
            "x": 53,
            "y": 63
        },
        {
            "demand": 11,
            "index": 154,
            "x": 98,
            "y": 60
        },
        {
            "demand": 18,
            "index": 155,
            "x": 99,
            "y": 58
        },
        {
            "demand": 17,
            "index": 156,
            "x": 92,
            "y": 23
        },
        {
            "demand": 16,
            "index": 157,
            "x": 65,
            "y": 47
        },
        {
            "demand": 14,
            "index": 158,
            "x": 92,
            "y": 39
        },
        {
            "demand": 12,
            "index": 159,
            "x": 78,
            "y": 23
        },
        {
            "demand": 11,
            "index": 160,
            "x": 53,
            "y": 53
        },
        {
            "demand": 19,
            "index": 161,
            "x": 90,
            "y": 35
        },
        {
            "demand": 15,
            "index": 162,
            "x": 91,
            "y": 68
        },
        {
            "demand": 18,
            "index": 163,
            "x": 55,
            "y": 67
        },
        {
            "demand": 19,
            "index": 164,
            "x": 74,
            "y": 23
        },
        {
            "demand": 17,
            "index": 165,
            "x": 59,
            "y": 72
        },
        {
            "demand": 14,
            "index": 166,
            "x": 74,
            "y": 44
        },
        {
            "demand": 17,
            "index": 167,
            "x": 68,
            "y": 37
        },
        {
            "demand": 14,
            "index": 168,
            "x": 72,
            "y": 38
        },
        {
            "demand": 13,
            "index": 169,
            "x": 92,
            "y": 43
        },
        {
            "demand": 20,
            "index": 170,
            "x": 76,
            "y": 25
        },
        {
            "demand": 17,
            "index": 171,
            "x": 62,
            "y": 24
        },
        {
            "demand": 11,
            "index": 172,
            "x": 61,
            "y": 38
        },
        {
            "demand": 17,
            "index": 173,
            "x": 79,
            "y": 48
        },
        {
            "demand": 14,
            "index": 174,
            "x": 73,
            "y": 37
        },
        {
            "demand": 16,
            "index": 175,
            "x": 91,
            "y": 72
        },
        {
            "demand": 16,
            "index": 176,
            "x": 52,
            "y": 28
        },
        {
            "demand": 12,
            "index": 177,
            "x": 94,
            "y": 69
        },
        {
            "demand": 20,
            "index": 178,
            "x": 49,
            "y": 28
        },
        {
            "demand": 20,
            "index": 179,
            "x": 58,
            "y": 35
        },
        {
            "demand": 18,
            "index": 180,
            "x": 93,
            "y": 48
        },
        {
            "demand": 16,
            "index": 181,
            "x": 91,
            "y": 45
        },
        {
            "demand": 12,
            "index": 182,
            "x": 67,
            "y": 54
        },
        {
            "demand": 16,
            "index": 183,
            "x": 59,
            "y": 71
        },
        {
            "demand": 15,
            "index": 184,
            "x": 63,
            "y": 37
        },
        {
            "demand": 18,
            "index": 185,
            "x": 91,
            "y": 56
        },
        {
            "demand": 20,
            "index": 186,
            "x": 79,
            "y": 71
        },
        {
            "demand": 17,
            "index": 187,
            "x": 50,
            "y": 66
        },
        {
            "demand": 18,
            "index": 188,
            "x": 70,
            "y": 33
        },
        {
            "demand": 12,
            "index": 189,
            "x": 67,
            "y": 75
        },
        {
            "demand": 12,
            "index": 190,
            "x": 89,
            "y": 56
        },
        {
            "demand": 11,
            "index": 191,
            "x": 55,
            "y": 47
        },
        {
            "demand": 13,
            "index": 192,
            "x": 65,
            "y": 51
        },
        {
            "demand": 20,
            "index": 193,
            "x": 69,
            "y": 70
        },
        {
            "demand": 20,
            "index": 194,
            "x": 85,
            "y": 56
        },
        {
            "demand": 20,
            "index": 195,
            "x": 70,
            "y": 27
        },
        {
            "demand": 17,
            "index": 196,
            "x": 100,
            "y": 53
        },
        {
            "demand": 16,
            "index": 197,
            "x": 87,
            "y": 36
        },
        {
            "demand": 19,
            "index": 198,
            "x": 78,
            "y": 30
        },
        {
            "demand": 18,
            "index": 199,
            "x": 74,
            "y": 40
        },
        {
            "demand": 12,
            "index": 200,
            "x": 57,
            "y": 47
        },
        {
            "demand": 19,
            "index": 201,
            "x": 97,
            "y": 45
        },
        {
            "demand": 13,
            "index": 202,
            "x": 50,
            "y": 51
        },
        {
            "demand": 15,
            "index": 203,
            "x": 50,
            "y": 58
        },
        {
            "demand": 19,
            "index": 204,
            "x": 49,
            "y": 65
        },
        {
            "demand": 11,
            "index": 205,
            "x": 87,
            "y": 55
        },
        {
            "demand": 19,
            "index": 206,
            "x": 74,
            "y": 69
        },
        {
            "demand": 16,
            "index": 207,
            "x": 61,
            "y": 54
        },
        {
            "demand": 14,
            "index": 208,
            "x": 75,
            "y": 44
        },
        {
            "demand": 18,
            "index": 209,
            "x": 100,
            "y": 62
        },
        {
            "demand": 15,
            "index": 210,
            "x": 64,
            "y": 73
        },
        {
            "demand": 16,
            "index": 211,
            "x": 75,
            "y": 52
        },
        {
            "demand": 17,
            "index": 212,
            "x": 93,
            "y": 54
        },
        {
            "demand": 11,
            "index": 213,
            "x": 82,
            "y": 37
        },
        {
            "demand": 13,
            "index": 214,
            "x": 84,
            "y": 53
        },
        {
            "demand": 15,
            "index": 215,
            "x": 65,
            "y": 53
        },
        {
            "demand": 19,
            "index": 216,
            "x": 77,
            "y": 70
        },
        {
            "demand": 15,
            "index": 217,
            "x": 68,
            "y": 54
        },
        {
            "demand": 18,
            "index": 218,
            "x": 83,
            "y": 73
        },
        {
            "demand": 20,
            "index": 219,
            "x": 60,
            "y": 28
        },
        {
            "demand": 12,
            "index": 220,
            "x": 60,
            "y": 59
        },
        {
            "demand": 13,
            "index": 221,
            "x": 72,
            "y": 23
        },
        {
            "demand": 13,
            "index": 222,
            "x": 99,
            "y": 59
        },
        {
            "demand": 14,
            "index": 223,
            "x": 83,
            "y": 59
        },
        {
            "demand": 18,
            "index": 224,
            "x": 49,
            "y": 72
        },
        {
            "demand": 20,
            "index": 225,
            "x": 53,
            "y": 39
        },
        {
            "demand": 13,
            "index": 226,
            "x": 96,
            "y": 62
        },
        {
            "demand": 16,
            "index": 227,
            "x": 81,
            "y": 63
        },
        {
            "demand": 17,
            "index": 228,
            "x": 49,
            "y": 38
        },
        {
            "demand": 11,
            "index": 229,
            "x": 70,
            "y": 24
        },
        {
            "demand": 17,
            "index": 230,
            "x": 53,
            "y": 31
        },
        {
            "demand": 13,
            "index": 231,
            "x": 67,
            "y": 47
        },
        {
            "demand": 13,
            "index": 232,
            "x": 58,
            "y": 48
        },
        {
            "demand": 12,
            "index": 233,
            "x": 86,
            "y": 39
        },
        {
            "demand": 11,
            "index": 234,
            "x": 70,
            "y": 26
        },
        {
            "demand": 17,
            "index": 235,
            "x": 92,
            "y": 67
        },
        {
            "demand": 19,
            "index": 236,
            "x": 72,
            "y": 55
        },
        {
            "demand": 16,
            "index": 237,
            "x": 56,
            "y": 47
        },
        {
            "demand": 12,
            "index": 238,
            "x": 94,
            "y": 48
        },
        {
            "demand": 18,
            "index": 239,
            "x": 67,
            "y": 60
        },
        {
            "demand": 11,
            "index": 240,
            "x": 59,
            "y": 32
        },
        {
            "demand": 16,
            "index": 241,
            "x": 55,
            "y": 52
        },
        {
            "demand": 11,
            "index": 242,
            "x": 90,
            "y": 50
        },
        {
            "demand": 15,
            "index": 243,
            "x": 50,
            "y": 69
        },
        {
            "demand": 14,
            "index": 244,
            "x": 67,
            "y": 61
        },
        {
            "demand": 11,
            "index": 245,
            "x": 80,
            "y": 70
        },
        {
            "demand": 13,
            "index": 246,
            "x": 50,
            "y": 74
        },
        {
            "demand": 19,
            "index": 247,
            "x": 52,
            "y": 73
        },
        {
            "demand": 14,
            "index": 248,
            "x": 82,
            "y": 29
        },
        {
            "demand": 13,
            "index": 249,
            "x": 52,
            "y": 36
        },
        {
            "demand": 11,
            "index": 250,
            "x": 84,
            "y": 70
        },
        {
            "demand": 15,
            "index": 251,
            "x": 87,
            "y": 24
        },
        {
            "demand": 16,
            "index": 252,
            "x": 96,
            "y": 56
        },
        {
            "demand": 18,
            "index": 253,
            "x": 56,
            "y": 31
        },
        {
            "demand": 13,
            "index": 254,
            "x": 74,
            "y": 70
        },
        {
            "demand": 20,
            "index": 255,
            "x": 58,
            "y": 47
        },
        {
            "demand": 11,
            "index": 256,
            "x": 55,
            "y": 58
        },
        {
            "demand": 14,
            "index": 257,
            "x": 55,
            "y": 72
        },
        {
            "demand": 16,
            "index": 258,
            "x": 86,
            "y": 62
        },
        {
            "demand": 11,
            "index": 259,
            "x": 92,
            "y": 46
        },
        {
            "demand": 19,
            "index": 260,
            "x": 58,
            "y": 58
        },
        {
            "demand": 16,
            "index": 261,
            "x": 82,
            "y": 54
        },
        {
            "demand": 13,
            "index": 262,
            "x": 73,
            "y": 73
        },
        {
            "demand": 14,
            "index": 263,
            "x": 60,
            "y": 31
        },
        {
            "demand": 11,
            "index": 264,
            "x": 57,
            "y": 41
        },
        {
            "demand": 15,
            "index": 265,
            "x": 68,
            "y": 34
        },
        {
            "demand": 18,
            "index": 266,
            "x": 98,
            "y": 45
        },
        {
            "demand": 17,
            "index": 267,
            "x": 69,
            "y": 24
        },
        {
            "demand": 19,
            "index": 268,
            "x": 92,
            "y": 73
        },
        {
            "demand": 12,
            "index": 269,
            "x": 51,
            "y": 63
        },
        {
            "demand": 17,
            "index": 270,
            "x": 59,
            "y": 43
        },
        {
            "demand": 14,
            "index": 271,
            "x": 74,
            "y": 46
        },
        {
            "demand": 19,
            "index": 272,
            "x": 53,
            "y": 74
        },
        {
            "demand": 15,
            "index": 273,
            "x": 79,
            "y": 76
        },
        {
            "demand": 15,
            "index": 274,
            "x": 70,
            "y": 65
        },
        {
            "demand": 11,
            "index": 275,
            "x": 71,
            "y": 47
        },
        {
            "demand": 13,
            "index": 276,
            "x": 50,
            "y": 40
        },
        {
            "demand": 18,
            "index": 277,
            "x": 86,
            "y": 41
        },
        {
            "demand": 14,
            "index": 278,
            "x": 100,
            "y": 60
        },
        {
            "demand": 12,
            "index": 279,
            "x": 63,
            "y": 67
        },
        {
            "demand": 12,
            "index": 280,
            "x": 61,
            "y": 23
        },
        {
            "demand": 17,
            "index": 281,
            "x": 76,
            "y": 67
        },
        {
            "demand": 15,
            "index": 282,
            "x": 82,
            "y": 75
        },
        {
            "demand": 11,
            "index": 283,
            "x": 73,
            "y": 28
        },
        {
            "demand": 19,
            "index": 284,
            "x": 75,
            "y": 54
        },
        {
            "demand": 14,
            "index": 285,
            "x": 88,
            "y": 27
        },
        {
            "demand": 18,
            "index": 286,
            "x": 29,
            "y": 87
        },
        {
            "demand": 14,
            "index": 287,
            "x": 17,
            "y": 86
        },
        {
            "demand": 12,
            "index": 288,
            "x": 48,
            "y": 67
        },
        {
            "demand": 20,
            "index": 289,
            "x": 18,
            "y": 92
        },
        {
            "demand": 12,
            "index": 290,
            "x": 46,
            "y": 79
        },
        {
            "demand": 12,
            "index": 291,
            "x": 14,
            "y": 70
        },
        {
            "demand": 17,
            "index": 292,
            "x": 45,
            "y": 72
        },
        {
            "demand": 18,
            "index": 293,
            "x": 15,
            "y": 73
        },
        {
            "demand": 11,
            "index": 294,
            "x": 36,
            "y": 76
        },
        {
            "demand": 11,
            "index": 295,
            "x": 7,
            "y": 75
        },
        {
            "demand": 17,
            "index": 296,
            "x": 49,
            "y": 70
        },
        {
            "demand": 14,
            "index": 297,
            "x": 43,
            "y": 85
        },
        {
            "demand": 13,
            "index": 298,
            "x": 23,
            "y": 86
        },
        {
            "demand": 13,
            "index": 299,
            "x": 41,
            "y": 81
        },
        {
            "demand": 20,
            "index": 300,
            "x": 9,
            "y": 76
        },
        {
            "demand": 15,
            "index": 301,
            "x": 13,
            "y": 66
        },
        {
            "demand": 17,
            "index": 302,
            "x": 28,
            "y": 67
        },
        {
            "demand": 12,
            "index": 303,
            "x": 38,
            "y": 88
        },
        {
            "demand": 20,
            "index": 304,
            "x": 7,
            "y": 96
        },
        {
            "demand": 20,
            "index": 305,
            "x": 19,
            "y": 92
        },
        {
            "demand": 15,
            "index": 306,
            "x": 33,
            "y": 81
        },
        {
            "demand": 20,
            "index": 307,
            "x": 24,
            "y": 74
        },
        {
            "demand": 16,
            "index": 308,
            "x": 21,
            "y": 80
        },
        {
            "demand": 13,
            "index": 309,
            "x": 5,
            "y": 96
        },
        {
            "demand": 18,
            "index": 310,
            "x": 48,
            "y": 94
        },
        {
            "demand": 16,
            "index": 311,
            "x": 13,
            "y": 76
        },
        {
            "demand": 19,
            "index": 312,
            "x": 8,
            "y": 71
        },
        {
            "demand": 17,
            "index": 313,
            "x": 3,
            "y": 67
        },
        {
            "demand": 13,
            "index": 314,
            "x": 19,
            "y": 74
        },
        {
            "demand": 17,
            "index": 315,
            "x": 10,
            "y": 94
        },
        {
            "demand": 14,
            "index": 316,
            "x": 8,
            "y": 92
        },
        {
            "demand": 20,
            "index": 317,
            "x": 25,
            "y": 71
        },
        {
            "demand": 18,
            "index": 318,
            "x": 44,
            "y": 100
        },
        {
            "demand": 17,
            "index": 319,
            "x": 6,
            "y": 93
        },
        {
            "demand": 12,
            "index": 320,
            "x": 3,
            "y": 71
        },
        {
            "demand": 15,
            "index": 321,
            "x": 39,
            "y": 88
        },
        {
            "demand": 12,
            "index": 322,
            "x": 37,
            "y": 83
        },
        {
            "demand": 15,
            "index": 323,
            "x": 13,
            "y": 65
        },
        {
            "demand": 17,
            "index": 324,
            "x": 11,
            "y": 76
        },
        {
            "demand": 11,
            "index": 325,
            "x": 34,
            "y": 99
        },
        {
            "demand": 15,
            "index": 326,
            "x": 50,
            "y": 68
        },
        {
            "demand": 14,
            "index": 327,
            "x": 39,
            "y": 70
        },
        {
            "demand": 14,
            "index": 328,
            "x": 25,
            "y": 95
        },
        {
            "demand": 15,
            "index": 329,
            "x": 30,
            "y": 90
        },
        {
            "demand": 15,
            "index": 330,
            "x": 49,
            "y": 66
        },
        {
            "demand": 12,
            "index": 331,
            "x": 1,
            "y": 98
        },
        {
            "demand": 13,
            "index": 332,
            "x": 31,
            "y": 83
        },
        {
            "demand": 16,
            "index": 333,
            "x": 18,
            "y": 86
        },
        {
            "demand": 16,
            "index": 334,
            "x": 51,
            "y": 97
        },
        {
            "demand": 17,
            "index": 335,
            "x": 11,
            "y": 86
        },
        {
            "demand": 20,
            "index": 336,
            "x": 30,
            "y": 83
        },
        {
            "demand": 11,
            "index": 337,
            "x": 22,
            "y": 100
        },
        {
            "demand": 13,
            "index": 338,
            "x": 8,
            "y": 83
        },
        {
            "demand": 19,
            "index": 339,
            "x": 51,
            "y": 100
        },
        {
            "demand": 15,
            "index": 340,
            "x": 17,
            "y": 100
        },
        {
            "demand": 20,
            "index": 341,
            "x": 16,
            "y": 93
        },
        {
            "demand": 18,
            "index": 342,
            "x": 12,
            "y": 100
        },
        {
            "demand": 14,
            "index": 343,
            "x": 31,
            "y": 71
        },
        {
            "demand": 11,
            "index": 344,
            "x": 35,
            "y": 64
        },
        {
            "demand": 14,
            "index": 345,
            "x": 13,
            "y": 82
        },
        {
            "demand": 18,
            "index": 346,
            "x": 15,
            "y": 86
        },
        {
            "demand": 16,
            "index": 347,
            "x": 26,
            "y": 81
        },
        {
            "demand": 19,
            "index": 348,
            "x": 19,
            "y": 82
        },
        {
            "demand": 11,
            "index": 349,
            "x": 27,
            "y": 72
        },
        {
            "demand": 19,
            "index": 350,
            "x": 33,
            "y": 88
        },
        {
            "demand": 15,
            "index": 351,
            "x": 5,
            "y": 83
        },
        {
            "demand": 15,
            "index": 352,
            "x": 8,
            "y": 99
        },
        {
            "demand": 16,
            "index": 353,
            "x": 24,
            "y": 95
        },
        {
            "demand": 11,
            "index": 354,
            "x": 15,
            "y": 78
        },
        {
            "demand": 20,
            "index": 355,
            "x": 31,
            "y": 66
        },
        {
            "demand": 19,
            "index": 356,
            "x": 5,
            "y": 99
        },
        {
            "demand": 18,
            "index": 357,
            "x": 15,
            "y": 74
        },
        {
            "demand": 11,
            "index": 358,
            "x": 22,
            "y": 72
        },
        {
            "demand": 15,
            "index": 359,
            "x": 8,
            "y": 72
        },
        {
            "demand": 17,
            "index": 360,
            "x": 21,
            "y": 85
        },
        {
            "demand": 14,
            "index": 361,
            "x": 44,
            "y": 77
        },
        {
            "demand": 18,
            "index": 362,
            "x": 45,
            "y": 69
        },
        {
            "demand": 17,
            "index": 363,
            "x": 31,
            "y": 100
        },
        {
            "demand": 20,
            "index": 364,
            "x": 42,
            "y": 94
        },
        {
            "demand": 14,
            "index": 365,
            "x": 9,
            "y": 93
        },
        {
            "demand": 19,
            "index": 366,
            "x": 4,
            "y": 89
        },
        {
            "demand": 15,
            "index": 367,
            "x": 40,
            "y": 98
        },
        {
            "demand": 14,
            "index": 368,
            "x": 13,
            "y": 99
        },
        {
            "demand": 14,
            "index": 369,
            "x": 6,
            "y": 97
        },
        {
            "demand": 11,
            "index": 370,
            "x": 34,
            "y": 87
        },
        {
            "demand": 20,
            "index": 371,
            "x": 47,
            "y": 90
        },
        {
            "demand": 18,
            "index": 372,
            "x": 13,
            "y": 97
        },
        {
            "demand": 16,
            "index": 373,
            "x": 39,
            "y": 85
        },
        {
            "demand": 12,
            "index": 374,
            "x": 14,
            "y": 77
        },
        {
            "demand": 14,
            "index": 375,
            "x": 34,
            "y": 97
        },
        {
            "demand": 17,
            "index": 376,
            "x": 44,
            "y": 84
        },
        {
            "demand": 17,
            "index": 377,
            "x": 45,
            "y": 64
        },
        {
            "demand": 20,
            "index": 378,
            "x": 45,
            "y": 88
        },
        {
            "demand": 15,
            "index": 379,
            "x": 51,
            "y": 75
        },
        {
            "demand": 12,
            "index": 380,
            "x": 16,
            "y": 67
        },
        {
            "demand": 11,
            "index": 381,
            "x": 31,
            "y": 91
        },
        {
            "demand": 18,
            "index": 382,
            "x": 27,
            "y": 77
        },
        {
            "demand": 14,
            "index": 383,
            "x": 51,
            "y": 82
        },
        {
            "demand": 15,
            "index": 384,
            "x": 8,
            "y": 70
        },
        {
            "demand": 14,
            "index": 385,
            "x": 7,
            "y": 69
        },
        {
            "demand": 19,
            "index": 386,
            "x": 6,
            "y": 86
        },
        {
            "demand": 12,
            "index": 387,
            "x": 40,
            "y": 89
        },
        {
            "demand": 14,
            "index": 388,
            "x": 43,
            "y": 87
        },
        {
            "demand": 15,
            "index": 389,
            "x": 11,
            "y": 63
        },
        {
            "demand": 11,
            "index": 390,
            "x": 23,
            "y": 100
        },
        {
            "demand": 16,
            "index": 391,
            "x": 10,
            "y": 88
        },
        {
            "demand": 20,
            "index": 392,
            "x": 45,
            "y": 84
        },
        {
            "demand": 17,
            "index": 393,
            "x": 40,
            "y": 88
        },
        {
            "demand": 14,
            "index": 394,
            "x": 17,
            "y": 85
        },
        {
            "demand": 12,
            "index": 395,
            "x": 36,
            "y": 73
        },
        {
            "demand": 19,
            "index": 396,
            "x": 29,
            "y": 91
        },
        {
            "demand": 14,
            "index": 397,
            "x": 42,
            "y": 99
        },
        {
            "demand": 19,
            "index": 398,
            "x": 23,
            "y": 95
        },
        {
            "demand": 18,
            "index": 399,
            "x": 3,
            "y": 63
        },
        {
            "demand": 12,
            "index": 400,
            "x": 27,
            "y": 68
        },
        {
            "demand": 18,
            "index": 401,
            "x": 43,
            "y": 66
        },
        {
            "demand": 12,
            "index": 402,
            "x": 37,
            "y": 87
        },
        {
            "demand": 14,
            "index": 403,
            "x": 49,
            "y": 86
        },
        {
            "demand": 16,
            "index": 404,
            "x": 29,
            "y": 83
        },
        {
            "demand": 18,
            "index": 405,
            "x": 26,
            "y": 84
        },
        {
            "demand": 16,
            "index": 406,
            "x": 45,
            "y": 92
        },
        {
            "demand": 19,
            "index": 407,
            "x": 18,
            "y": 93
        },
        {
            "demand": 14,
            "index": 408,
            "x": 37,
            "y": 88
        },
        {
            "demand": 16,
            "index": 409,
            "x": 50,
            "y": 79
        },
        {
            "demand": 18,
            "index": 410,
            "x": 21,
            "y": 66
        },
        {
            "demand": 19,
            "index": 411,
            "x": 2,
            "y": 71
        },
        {
            "demand": 15,
            "index": 412,
            "x": 13,
            "y": 89
        },
        {
            "demand": 14,
            "index": 413,
            "x": 21,
            "y": 74
        },
        {
            "demand": 20,
            "index": 414,
            "x": 31,
            "y": 76
        },
        {
            "demand": 13,
            "index": 415,
            "x": 11,
            "y": 69
        },
        {
            "demand": 18,
            "index": 416,
            "x": 51,
            "y": 84
        },
        {
            "demand": 13,
            "index": 417,
            "x": 4,
            "y": 72
        },
        {
            "demand": 16,
            "index": 418,
            "x": 27,
            "y": 74
        },
        {
            "demand": 12,
            "index": 419,
            "x": 33,
            "y": 90
        }
    ],
    "depots": [
        {
            "capacity": 630,
            "costs": 135507,
            "index": 0,
            "x": 36,
            "y": 87
        },
        {
            "capacity": 633,
            "costs": 151104,
            "index": 1,
            "x": 43,
            "y": 76
        },
        {
            "capacity": 629,
            "costs": 162591,
            "index": 2,
            "x": 41,
            "y": 55
        },
        {
            "capacity": 621,
            "costs": 158344,
            "index": 3,
            "x": 23,
            "y": 73
        },
        {
            "capacity": 623,
            "costs": 147472,
            "index": 4,
            "x": 78,
            "y": 12
        },
        {
            "capacity": 626,
            "costs": 159628,
            "index": 5,
            "x": 26,
            "y": 80
        },
        {
            "capacity": 626,
            "costs": 160795,
            "index": 6,
            "x": 32,
            "y": 75
        },
        {
            "capacity": 629,
            "costs": 157915,
            "index": 7,
            "x": 9,
            "y": 71
        },
        {
            "capacity": 623,
            "costs": 155546,
            "index": 8,
            "x": 25,
            "y": 14
        },
        {
            "capacity": 628,
            "costs": 136566,
            "index": 9,
            "x": 99,
            "y": 89
        },
        {
            "capacity": 630,
            "costs": 155230,
            "index": 10,
            "x": 11,
            "y": 22
        },
        {
            "capacity": 624,
            "costs": 133202,
            "index": 11,
            "x": 99,
            "y": 38
        },
        {
            "capacity": 629,
            "costs": 168707,
            "index": 12,
            "x": 100,
            "y": 59
        },
        {
            "capacity": 628,
            "costs": 164904,
            "index": 13,
            "x": 27,
            "y": 6
        },
        {
            "capacity": 630,
            "costs": 150595,
            "index": 14,
            "x": 73,
            "y": 86
        },
        {
            "capacity": 627,
            "costs": 159220,
            "index": 15,
            "x": 79,
            "y": 55
        },
        {
            "capacity": 630,
            "costs": 154974,
            "index": 16,
            "x": 92,
            "y": 60
        },
        {
            "capacity": 626,
            "costs": 153427,
            "index": 17,
            "x": 73,
            "y": 59
        },
        {
            "capacity": 627,
            "costs": 130309,
            "index": 18,
            "x": 23,
            "y": 89
        },
        {
            "capacity": 633,
            "costs": 160030,
            "index": 19,
            "x": 3,
            "y": 87
        }
    ],
    "name": "400-20-3d",
    "type": "schneider",
    "vehicle_capacity": 70,
    "vehicle_costs": 1000
}